[
    {
        "title": "Multi-Vendor Shopping Web App",
        "imageSrc": "Assets/projetImage.png",
        "description": "This is a responsive Mern stack Multi-vendor Shopping Web App, that allows multiple sellers and buyers to own an account and also send & receive messages",
        "skills": [
            "React",
            "Express",
            "Node",
            "Mongo db",
            "Tailwind",
            "socket.io",
            "cloudinary"
        ],
        "demo": "https://chireva-frontend.vercel.app",
        "source": "https://github.com/chikephils/chireva"
    },
    {
        "title": "Project B",
        "imageSrc": "Assets/image.png",
        "description": "This is a project made to learn the latest languages by building an app.",
        "skills": [
            "React",
            "Express",
            "Node",
            "Sass"
        ],
        "demo": "https://www.example.com",
        "source": "https://www.github.com"
    },
    {
        "title": "Project C",
        "imageSrc": "Assets/image.png",
        "description": "This is a project made to learn the latest languages by building an app.",
        "skills": [
            "React",
            "Express",
            "Node"
        ],
        "demo": "https://www.example.com",
        "source": "https://www.github.com"
    }
]